momodeltool/__init__.py
momodeltool/model_process.py
momodeltool/momodeltool.py
momodeltool/visualization.py
momodeltool/__pycache__/__init__.cpython-38.pyc
momodeltool/__pycache__/momodeltool.cpython-38.pyc
momodeltool-0.0.17.dist-info/LICENSE
momodeltool-0.0.17.dist-info/METADATA
momodeltool-0.0.17.dist-info/WHEEL
momodeltool-0.0.17.dist-info/top_level.txt
momodeltool-0.0.17.dist-info/RECORD
