Metadata-Version: 2.1
Name: momodeltool
Version: 0.0.17
Summary: A small example package
Home-page: https://github.com/
Author: momodeltool
Author-email: JekkeySun <jianqi.sun@metoak.net>
Project-URL: Homepage, https://github.com/pypa/sampleproject
Project-URL: Bug Tracker, https://github.com/pypa/sampleproject/issues
Classifier: Programming Language :: Python :: 3
Classifier: License :: OSI Approved :: MIT License
Classifier: Operating System :: OS Independent
Requires-Python: >=3.8
License-File: LICENSE
Requires-Dist: opencv-python
Requires-Dist: numpy
Requires-Dist: torch
